<!--
  低速智能车 NavigateToPose 行为树。

  基于 Navigation2 Humble 默认的
  navigate_to_pose_w_replanning_and_recovery.xml，去掉 BackUp：车尾没有可靠
  障碍感知，倒车恢复会绕过 DWB 的 min_vel_x=0，不能安全使用。

  三次系统恢复依次为：清空局部/全局代价地图、原地旋转、短暂等待。
-->
<root main_tree_to_execute="MainTree">
  <BehaviorTree ID="MainTree">
    <RecoveryNode number_of_retries="3" name="NavigateRecovery">
      <PipelineSequence name="NavigateWithReplanning">
        <RateController hz="1.0">
          <RecoveryNode number_of_retries="1" name="ComputePathToPose">
            <ComputePathToPose goal="{goal}" path="{path}" planner_id="GridBased"/>
            <ClearEntireCostmap name="ClearGlobalCostmap-Context"
              service_name="global_costmap/clear_entirely_global_costmap"/>
          </RecoveryNode>
        </RateController>
        <!-- 控制失败直接进入下面的系统恢复，避免默认树先原地重复等待一轮。 -->
        <FollowPath path="{path}" controller_id="FollowPath"/>
      </PipelineSequence>
      <ReactiveFallback name="RecoveryFallback">
        <GoalUpdated/>
        <RoundRobin name="RecoveryActions">
          <Sequence name="ClearingActions">
            <ClearEntireCostmap name="ClearLocalCostmap-Subtree"
              service_name="local_costmap/clear_entirely_local_costmap"/>
            <ClearEntireCostmap name="ClearGlobalCostmap-Subtree"
              service_name="global_costmap/clear_entirely_global_costmap"/>
          </Sequence>
          <Spin spin_dist="1.57"/>
          <Wait wait_duration="2"/>
        </RoundRobin>
      </ReactiveFallback>
    </RecoveryNode>
  </BehaviorTree>
</root>
